{"Colors":[
{"ColorName":"Orange","ColorValue":"#F78F1E"},
{"ColorName":"Red","ColorValue":"#FF0000"},
{"ColorName":"Black","ColorValue":"#000000"},
{"ColorName":"White","ColorValue":"#FFFFFF"},
{"ColorName":"Gray","ColorValue":"#6C6C6C"},
{"ColorName":"LightGray","ColorValue":"#8C8C8C"},
{"ColorName":"FBColor","ColorValue":"#3B5998"},
{"ColorName":"LinkedinColor","ColorValue":"#0077B5"},
{"ColorName":"WhiteTransparent30","ColorValue":"#30FFFFFF"},
{"ColorName":"BlackTransparent30","ColorValue":"#30000000"}
]}